MANIFEST.in
README.txt
setup.py
collective/.DS_Store
collective/__init__.py
collective.routes.egg-info/PKG-INFO
collective.routes.egg-info/SOURCES.txt
collective.routes.egg-info/dependency_links.txt
collective.routes.egg-info/entry_points.txt
collective.routes.egg-info/namespace_packages.txt
collective.routes.egg-info/not-zip-safe
collective.routes.egg-info/paster_plugins.txt
collective.routes.egg-info/requires.txt
collective.routes.egg-info/top_level.txt
collective/routes/__init__.py
collective/routes/configure.zcml
collective/routes/content.py
collective/routes/controlpanel.py
collective/routes/finders.py
collective/routes/interfaces.py
collective/routes/routes.png
collective/routes/testing.py
collective/routes/traverser.py
collective/routes/upgrades.py
collective/routes/upgrades.zcml
collective/routes/utils.py
collective/routes/views.py
collective/routes/Extensions/Install.py
collective/routes/locales/collective.routes.pot
collective/routes/locales/manual.pot
collective/routes/locales/update.sh
collective/routes/locales/es/LC_MESSAGES/collective.routes.po
collective/routes/locales/it/LC_MESSAGES/collective.routes.po
collective/routes/locales/pt_BR/LC_MESSAGES/collective.routes.po
collective/routes/profiles/default/browserlayer.xml
collective/routes/profiles/default/controlpanel.xml
collective/routes/profiles/default/metadata.xml
collective/routes/profiles/default/registry.xml
collective/routes/profiles/uninstall/controlpanel.xml
collective/routes/profiles/uninstall/propertiestool.xml
collective/routes/tests/__init__.py
collective/routes/tests/test_registry.py
collective/routes/tests/test_routes.py
docs/HISTORY.txt
docs/INSTALL.txt
docs/LICENSE.GPL
docs/LICENSE.txt