Metadata-Version: 1.1
Name: collective.routes
Version: 1.1a2
Summary: ability to add route configuration for plone
Home-page: https://github.com/collective/collective.routes
Author: Nathan Van Gheem
Author-email: vangheem@gmail.com
License: GPL
Keywords: plone routes query path
Platform: UNKNOWN
Classifier: Framework :: Plone
Classifier: Programming Language :: Python
